{
    "status": "200",
    "message": "Section data get successful",
    "data": [
         {
            "id": 2,
            "title": "banner",
            "description": "this is the banner section",
            "keywords": "SliderBanner",
            "keyword_option": "",
            "end_point": "slider_container.json",
            "order": 2,
            "dlink": "http://fsdfsfasfsdfsdfsfd.com",
            "status": "active"
        },
        {
            "id": 1,
            "title": "advertise",
            "description": "this is the advertise section",
            "keywords": "Advertise1",
            "keyword_option": "",
            "end_point": "notification_api",
            "order": 1,
            "dlink": "http://fsdfsfasfsdfsdfsfd.com",
            "status": "active"
        },
         {
            "id": 2,
            "title": "advertise",
            "description": "this is the advertise section",
            "keywords": "Advertise",
            "keyword_option": "",
            "end_point": "notification_api",
            "order": 3,
            "dlink": "http://fsdfsfasfsdfsdfsfd.com",
            "status": "active"
        },
       
        {
            "id": 3,
            "title": "categories",
            "description": "this is the categories section",
            "keywords": "Categories",
            "keyword_option": "",
            "end_point": "categories_api.json",
            "order": 4,
            "dlink": "http://fsdfsfasfsdfsdfsfd.com",
            "status": "active"
        },
        {
            "id": 4,
            "title": "trending product",
            "description": "this is the product section",
            "keywords": "Product",
            "keyword_option": "MOST-VIEWED",
            "end_point": "product",
            "order": 6,
            "dlink": "http://fsdfsfasfsdfsdfsfd.com",
            "status": "active"
        },
        
        {
            "id": 6,
            "title": "offer",
            "description": "this is the offer section",
            "keywords": "Offer",
            "keyword_option": "",
            "end_point": "offer_api.json",
            "order": 5,
            "dlink": "http://fsdfsfasfsdfsdfsfd.com",
            "status": "active"
        },
           {
            "id": 2,
            "title": "banner",
            "description": "this is the banner section",
            "keywords": "SliderBanner",
            "keyword_option": "",
            "end_point": "slider_container.json",
            "order": 7,
            "dlink": "http://fsdfsfasfsdfsdfsfd.com",
            "status": "active"
        },
        {
            "id": 3,
            "title": "categories",
            "description": "this is the categories section",
            "keywords": "Categories",
            "keyword_option": "",
            "end_point": "categories_api.json",
            "order": 9,
            "dlink": "http://fsdfsfasfsdfsdfsfd.com",
            "status": "active"
        },
        {
            "id": 4,
            "title": "trending product",
            "description": "this is the product section",
            "keywords": "Product",
            "keyword_option": "MOST-VIEWED",
            "end_point": "product",
            "order": 8,
            "dlink": "http://fsdfsfasfsdfsdfsfd.com",
            "status": "active"
        },
        
        {
            "id": 6,
            "title": "offer",
            "description": "this is the offer section",
            "keywords": "Offer",
            "keyword_option": "",
            "end_point": "offer_api.json",
            "order": 10,
            "dlink": "http://fsdfsfasfsdfsdfsfd.com",
            "status": "active"
        },
        
    ]
}
